pycaw/__init__.py
pycaw/callbacks.py
pycaw/constants.py
pycaw/magic.py
pycaw/pycaw.py
pycaw/utils.py
pycaw/api/__init__.py
pycaw/api/audioclient/__init__.py
pycaw/api/audioclient/depend.py
pycaw/api/audiopolicy/__init__.py
pycaw/api/endpointvolume/__init__.py
pycaw/api/endpointvolume/depend.py
pycaw/api/mmdeviceapi/__init__.py
pycaw/api/mmdeviceapi/depend/__init__.py
pycaw/api/mmdeviceapi/depend/structures.py
pycaw-20230407.dist-info/LICENSE
pycaw-20230407.dist-info/METADATA
pycaw-20230407.dist-info/WHEEL
pycaw-20230407.dist-info/top_level.txt
pycaw-20230407.dist-info/RECORD
