Metadata-Version: 2.1
Name: pycaw
Version: 20230407
Summary: Python Core Audio Windows Library
Home-page: https://github.com/AndreMiras/pycaw
Author: Andre Miras
License-File: LICENSE
Requires-Dist: comtypes
Requires-Dist: psutil
